{"prodi_count":"5","web":"https://pmb.uinbanten.ac.id/","data":[{"no":"1","kode":"13121001","nama":"FISIKA","jenjang":"Sarjana","tampung":14,"peminat":10,"peluang":140.0},{"no":"2","kode":"13121002","nama":"BIOLOGI","jenjang":"Sarjana","tampung":28,"peminat":46,"peluang":60.87},{"no":"3","kode":"13121003","nama":"INFORMATIKA","jenjang":"Sarjana","tampung":48,"peminat":166,"peluang":28.92},{"no":"4","kode":"13121004","nama":"MATEMATIKA","jenjang":"Sarjana","tampung":14,"peminat":21,"peluang":66.67},{"no":"5","kode":"13121005","nama":"KIMIA","jenjang":"Sarjana","tampung":14,"peminat":16,"peluang":87.5}]}