{"prodi_count":"23","web":"https://pmb.uinsa.ac.id/pengumuman","data":[{"no":"1","kode":"13861001","nama":"PENDIDIKAN MATEMATIKA","jenjang":"Sarjana","tampung":52,"peminat":68,"peluang":76.47},{"no":"2","kode":"13861002","nama":"TEKNIK LINGKUNGAN","jenjang":"Sarjana","tampung":65,"peminat":188,"peluang":34.57},{"no":"3","kode":"13861003","nama":"ARSITEKTUR","jenjang":"Sarjana","tampung":65,"peminat":111,"peluang":58.56},{"no":"4","kode":"13861004","nama":"SISTEM INFORMASI","jenjang":"Sarjana","tampung":65,"peminat":217,"peluang":29.95},{"no":"5","kode":"13861005","nama":"ILMU KELAUTAN","jenjang":"Sarjana","tampung":65,"peminat":79,"peluang":82.28},{"no":"6","kode":"13861006","nama":"BIOLOGI","jenjang":"Sarjana","tampung":65,"peminat":94,"peluang":69.15},{"no":"7","kode":"13861007","nama":"MATEMATIKA","jenjang":"Sarjana","tampung":42,"peminat":35,"peluang":120.0},{"no":"8","kode":"13861008","nama":"PENDIDIKAN ILMU PENGETAHUAN ALAM","jenjang":"Sarjana","tampung":47,"peminat":127,"peluang":37.01},{"no":"9","kode":"13861009","nama":"TEKNIK SIPIL","jenjang":"Sarjana","tampung":65,"peminat":160,"peluang":40.62},{"no":"10","kode":"13861010","nama":"PENDIDIKAN BAHASA INGGRIS","jenjang":"Sarjana","tampung":65,"peminat":148,"peluang":43.92},{"no":"11","kode":"13861014","nama":"SOSIOLOGI","jenjang":"Sarjana","tampung":107,"peminat":179,"peluang":59.78},{"no":"12","kode":"13861015","nama":"ILMU KOMUNIKASI","jenjang":"Sarjana","tampung":112,"peminat":322,"peluang":34.78},{"no":"13","kode":"13861016","nama":"PSIKOLOGI","jenjang":"Sarjana","tampung":132,"peminat":488,"peluang":27.05},{"no":"14","kode":"13861032","nama":"SASTRA INGGRIS","jenjang":"Sarjana","tampung":82,"peminat":99,"peluang":82.83},{"no":"15","kode":"13861033","nama":"ILMU EKONOMI","jenjang":"Sarjana","tampung":80,"peminat":185,"peluang":43.24},{"no":"16","kode":"13861034","nama":"AKUNTANSI","jenjang":"Sarjana","tampung":97,"peminat":257,"peluang":37.74},{"no":"17","kode":"13861035","nama":"MANAJEMEN","jenjang":"Sarjana","tampung":105,"peminat":404,"peluang":25.99},{"no":"18","kode":"13861036","nama":"ILMU POLITIK","jenjang":"Sarjana","tampung":57,"peminat":84,"peluang":67.86},{"no":"19","kode":"13861037","nama":"HUBUNGAN INTERNASIONAL","jenjang":"Sarjana","tampung":87,"peminat":106,"peluang":82.08},{"no":"20","kode":"13861040","nama":"SASTRA INDONESIA","jenjang":"Sarjana","tampung":62,"peminat":115,"peluang":53.91},{"no":"21","kode":"13861041","nama":"HUKUM","jenjang":"Sarjana","tampung":107,"peminat":246,"peluang":43.5},{"no":"22","kode":"13861042","nama":"GIZI","jenjang":"Sarjana","tampung":80,"peminat":315,"peluang":25.4},{"no":"23","kode":"13861043","nama":"KEDOKTERAN","jenjang":"Sarjana","tampung":25,"peminat":null,"peluang":null}]}