{"kode":"1711","nama":"UNIVERSITAS HASANUDDIN","prodi_count":"88","web":"https://regpmb.unhas.ac.id","match_stats":{"total":88,"matched":74,"unmatched":14},"data":[{"no":"1","kode":"17111001","nama":"MATEMATIKA","jenjang":"Sarjana","tampung":44,"peminat":124,"peluang":35.48,"akreditasi":{"nilai":"Unggul","no_sk":"167/SK/LAMSAMA/Akred/S/VI/2025","tahun":"2025","tgl_expired":"2030-06-22","status":"Masih berlaku","jenjang_akred":"S1","match_method":"exact"}},{"no":"2","kode":"17111002","nama":"FISIKA","jenjang":"Sarjana","tampung":44,"peminat":79,"peluang":55.7,"akreditasi":{"nilai":"Unggul","no_sk":"074/SK/LAMSAMA/Akred/S/VII/2023","tahun":"2023","tgl_expired":"2028-07-20","status":"Masih berlaku","jenjang_akred":"S1","match_method":"exact"}},{"no":"3","kode":"17111003","nama":"KESEHATAN MASYARAKAT","jenjang":"Sarjana","tampung":175,"peminat":1961,"peluang":8.92,"akreditasi":{"nilai":"Unggul","no_sk":"0774/LAM-PTKes/Akr/Sar/IX/2022","tahun":"2022","tgl_expired":"2027-09-08","status":"Masih berlaku","jenjang_akred":"S1","match_method":"exact"}},{"no":"4","kode":"17111004","nama":"FARMASI","jenjang":"Sarjana","tampung":90,"peminat":1746,"peluang":5.15,"akreditasi":{"nilai":"Unggul","no_sk":"0399/LAM-PTKes/Akr/Sar/VI/2022","tahun":"2022","tgl_expired":"2027-06-09","status":"Masih berlaku","jenjang_akred":"S1","match_method":"exact"}},{"no":"5","kode":"17111005","nama":"KIMIA","jenjang":"Sarjana","tampung":55,"peminat":214,"peluang":25.7,"akreditasi":{"nilai":"Unggul","no_sk":"070/SK/LAMSAMA/Akred/S/VII/2023","tahun":"2023","tgl_expired":"2028-07-17","status":"Masih berlaku","jenjang_akred":"S1","match_method":"exact"}},{"no":"6","kode":"17111006","nama":"BIOLOGI","jenjang":"Sarjana","tampung":66,"peminat":216,"peluang":30.56,"akreditasi":{"nilai":"Unggul","no_sk":"055/SK/LAMSAMA/Akred/S/VII/2023","tahun":"2023","tgl_expired":"2028-07-06","status":"Masih berlaku","jenjang_akred":"S1","match_method":"exact"}},{"no":"7","kode":"17111007","nama":"PENDIDIKAN DOKTER","jenjang":"Sarjana","tampung":132,"peminat":3172,"peluang":4.16,"akreditasi":{"nilai":"Unggul","no_sk":"0550/LAM-PTKes/Akr/Sar/VII/2022","tahun":"2022","tgl_expired":"2026-08-26","status":"143 hari lagi kadaluarsa","jenjang_akred":"S1","match_method":"partial"}},{"no":"8","kode":"17111008","nama":"AGROTEKNOLOGI","jenjang":"Sarjana","tampung":110,"peminat":470,"peluang":23.4,"akreditasi":{"nilai":"Unggul","no_sk":"8074/SK/BAN-PT/Ak.Ppj/S/X/2022","tahun":"2022","tgl_expired":"2027-11-01","status":"Masih berlaku","jenjang_akred":"S1","match_method":"exact"}},{"no":"9","kode":"17111009","nama":"ILMU DAN TEKNOLOGI PANGAN","jenjang":"Sarjana","tampung":70,"peminat":408,"peluang":17.16,"akreditasi":{"nilai":"Unggul","no_sk":"7121/SK/BAN-PT/Ak.Ppj/S/X/2022","tahun":"2022","tgl_expired":"2027-10-25","status":"Masih berlaku","jenjang_akred":"S1","match_method":"exact"}},{"no":"10","kode":"17111010","nama":"AGRIBISNIS","jenjang":"Sarjana","tampung":95,"peminat":576,"peluang":16.49,"akreditasi":{"nilai":"Unggul","no_sk":"5800/SK/BAN-PT/Ak.Ppj/S/VIII/2022","tahun":"2022","tgl_expired":"2027-09-13","status":"Masih berlaku","jenjang_akred":"S1","match_method":"exact"}},{"no":"11","kode":"17111011","nama":"TEKNIK PERTANIAN","jenjang":"Sarjana","tampung":67,"peminat":311,"peluang":21.54,"akreditasi":{"nilai":"Unggul","no_sk":"8071/SK/BAN-PT/Ak.Ppj/S/X/2022","tahun":"2022","tgl_expired":"2027-11-01","status":"Masih berlaku","jenjang_akred":"S1","match_method":"exact"}},{"no":"12","kode":"17111012","nama":"TEKNIK SIPIL","jenjang":"Sarjana","tampung":76,"peminat":1137,"peluang":6.68,"akreditasi":{"nilai":"Unggul","no_sk":"2087/SK/BAN-PT/Akred-PMT/S/III/2022","tahun":"2022","tgl_expired":"2027-03-30","status":"Masih berlaku","jenjang_akred":"S1","match_method":"exact"}},{"no":"13","kode":"17111013","nama":"TEKNIK MESIN","jenjang":"Sarjana","tampung":65,"peminat":585,"peluang":11.11,"akreditasi":{"nilai":"Unggul","no_sk":"1698/SK/BAN-PT/Ak-PPJ/S/III/2022","tahun":"2022","tgl_expired":"2027-03-30","status":"Masih berlaku","jenjang_akred":"S1","match_method":"exact"}},{"no":"14","kode":"17111014","nama":"TEKNIK ELEKTRO","jenjang":"Sarjana","tampung":95,"peminat":746,"peluang":12.73,"akreditasi":{"nilai":"Unggul","no_sk":"0802/SK/LAM Teknik/AS/XII/2024","tahun":"2024","tgl_expired":"2029-12-20","status":"Masih berlaku","jenjang_akred":"S1","match_method":"exact"}},{"no":"15","kode":"17111015","nama":"TEKNIK PERKAPALAN","jenjang":"Sarjana","tampung":55,"peminat":334,"peluang":16.47,"akreditasi":{"nilai":"Unggul","no_sk":"0059/SK/LAM Teknik/AS/VIII/2022","tahun":"2022","tgl_expired":"2027-08-20","status":"Masih berlaku","jenjang_akred":"S1","match_method":"exact"}},{"no":"16","kode":"17111016","nama":"TEKNIK GEOLOGI","jenjang":"Sarjana","tampung":65,"peminat":914,"peluang":7.11,"akreditasi":{"nilai":"Unggul","no_sk":"12579/SK/BAN-PT/AK-ISK/S/XI/2021","tahun":"2021","tgl_expired":"2026-08-19","status":"136 hari lagi kadaluarsa","jenjang_akred":"S1","match_method":"exact"}},{"no":"17","kode":"17111017","nama":"PENDIDIKAN DOKTER GIGI","jenjang":"Sarjana","tampung":80,"peminat":1895,"peluang":4.22,"akreditasi":{"nilai":"Unggul","no_sk":"0550/LAM-PTKes/Akr/Sar/VII/2022","tahun":"2022","tgl_expired":"2026-08-26","status":"143 hari lagi kadaluarsa","jenjang_akred":"S1","match_method":"exact"}},{"no":"18","kode":"17111018","nama":"TEKNIK ARSITEKTUR","jenjang":"Sarjana","tampung":60,"peminat":497,"peluang":12.07,"akreditasi":{"nilai":"Unggul","no_sk":"10813/SK/BAN-PT/AK-ISK/S/IX/2021","tahun":"2021","tgl_expired":"2026-06-18","status":"74 hari lagi kadaluarsa","jenjang_akred":"S1","match_method":"partial"}},{"no":"19","kode":"17111019","nama":"KEHUTANAN","jenjang":"Sarjana","tampung":162,"peminat":677,"peluang":23.93,"akreditasi":{"nilai":"Unggul","no_sk":"5614/SK/BAN-PT/Ak.Ppj/S/VIII/2022","tahun":"2022","tgl_expired":"2027-08-23","status":"Masih berlaku","jenjang_akred":"S1","match_method":"exact"}},{"no":"20","kode":"17111020","nama":"GEOFISIKA","jenjang":"Sarjana","tampung":55,"peminat":189,"peluang":29.1,"akreditasi":{"nilai":"Unggul","no_sk":"085/SK/LAMSAMA/Akred/S/III/2026","tahun":"2026","tgl_expired":"2028-03-24","status":"Masih berlaku","jenjang_akred":"S1","match_method":"exact"}},{"no":"21","kode":"17111021","nama":"STATISTIKA","jenjang":"Sarjana","tampung":44,"peminat":312,"peluang":14.1,"akreditasi":{"nilai":"Unggul","no_sk":"015/SK/LAMSAMA/Akred/S/III/2024","tahun":"2024","tgl_expired":"2029-03-20","status":"Masih berlaku","jenjang_akred":"S1","match_method":"exact"}},{"no":"22","kode":"17111022","nama":"ILMU GIZI","jenjang":"Sarjana","tampung":75,"peminat":997,"peluang":7.52,"akreditasi":{"nilai":"Unggul","no_sk":"0078/LAM-PTKes/Akr/Sar/I/2023","tahun":"2023","tgl_expired":"2028-01-26","status":"Masih berlaku","jenjang_akred":"S1","match_method":"exact"}},{"no":"23","kode":"17111023","nama":"ILMU KELAUTAN","jenjang":"Sarjana","tampung":122,"peminat":224,"peluang":54.46,"akreditasi":{"nilai":"Unggul","no_sk":"6088/SK/BAN-PT/Ak.Ppj/S/X/2024","tahun":"2024","tgl_expired":"2029-10-16","status":"Masih berlaku","jenjang_akred":"S1","match_method":"exact"}},{"no":"24","kode":"17111024","nama":"BUDIDAYA PERAIRAN","jenjang":"Sarjana","tampung":60,"peminat":86,"peluang":69.77,"akreditasi":{"nilai":"Unggul","no_sk":"8198/SK/BAN-PT/Ak.Ppj/S/XI/2025","tahun":"2025","tgl_expired":"2030-11-16","status":"Masih berlaku","jenjang_akred":"S1","match_method":"exact"}},{"no":"25","kode":"17111025","nama":"MANAJEMEN SUMBERDAYA PERAIRAN","jenjang":"Sarjana","tampung":64,"peminat":116,"peluang":55.17,"akreditasi":{"nilai":"Unggul","no_sk":"491/DE/A.5/AR.10/VI/2023","tahun":"2023","tgl_expired":"2028-06-23","status":"Masih berlaku","jenjang_akred":"S1","match_method":"partial"}},{"no":"26","kode":"17111026","nama":"PEMANFAATAN SUMBERDAYA PERIKANAN","jenjang":"Sarjana","tampung":47,"peminat":68,"peluang":69.12,"akreditasi":{"nilai":"Unggul","no_sk":"14/SK/BAN-PT/Ak.Ppj/S/I/2026","tahun":"2026","tgl_expired":"2030-12-14","status":"Masih berlaku","jenjang_akred":"S1","match_method":"fuzzy"}},{"no":"27","kode":"17111027","nama":"AGROBISNIS PERIKANAN","jenjang":"Sarjana","tampung":76,"peminat":143,"peluang":53.15,"akreditasi":{"nilai":"Unggul","no_sk":"5586/SK/BAN-PT/Ak.KP/S/VIII/2024","tahun":"2024","tgl_expired":"2027-01-31","status":"Masih berlaku","jenjang_akred":"S1","match_method":"exact"}},{"no":"28","kode":"17111028","nama":"ILMU KEPERAWATAN","jenjang":"Sarjana","tampung":87,"peminat":1062,"peluang":8.19,"akreditasi":{"nilai":"UNGGUL","no_sk":"0315/LAM-PTKes/Akr/Sar/V/2024","tahun":"2024","tgl_expired":"2029-05-29","status":"Masih berlaku","jenjang_akred":"S1","match_method":"exact"}},{"no":"29","kode":"17111029","nama":"PETERNAKAN","jenjang":"Sarjana","tampung":225,"peminat":387,"peluang":58.14,"akreditasi":{"nilai":"Unggul","no_sk":"5844/SK/BAN-PT/Ak.Ppj/S/IX/2024","tahun":"2024","tgl_expired":"2029-09-25","status":"Masih berlaku","jenjang_akred":"S1","match_method":"exact"}},{"no":"30","kode":"17111030","nama":"TEKNIK KELAUTAN","jenjang":"Sarjana","tampung":77,"peminat":191,"peluang":40.31,"akreditasi":{"nilai":"Unggul","no_sk":"0104/SK/LAM Teknik/AS/IV/2025","tahun":"2025","tgl_expired":"2030-04-20","status":"Masih berlaku","jenjang_akred":"S1","match_method":"exact"}},{"no":"31","kode":"17111031","nama":"TEKNIK INDUSTRI","jenjang":"Sarjana","tampung":60,"peminat":1043,"peluang":5.75,"akreditasi":{"nilai":"Unggul","no_sk":"0289/SK/LAM Teknik/AS/VIII/2023","tahun":"2023","tgl_expired":"2028-08-20","status":"Masih berlaku","jenjang_akred":"S1","match_method":"exact"}},{"no":"32","kode":"17111032","nama":"TEKNIK SISTEM PERKAPALAN","jenjang":"Sarjana","tampung":62,"peminat":196,"peluang":31.63,"akreditasi":{"nilai":"Unggul","no_sk":"0516/SK/LAM Teknik/AS/VIII/2025","tahun":"2025","tgl_expired":"2030-08-20","status":"Masih berlaku","jenjang_akred":"S1","match_method":"exact"}},{"no":"33","kode":"17111033","nama":"PERENCANAAN WILAYAH DAN KOTA","jenjang":"Sarjana","tampung":50,"peminat":388,"peluang":12.89,"akreditasi":{"nilai":"Unggul","no_sk":"2291/SK/BAN-PT/Akred-Itnl/S/VI/2023","tahun":"2023","tgl_expired":"2027-09-30","status":"Masih berlaku","jenjang_akred":"S1","match_method":"exact"}},{"no":"34","kode":"17111034","nama":"TEKNIK PERTAMBANGAN","jenjang":"Sarjana","tampung":58,"peminat":2065,"peluang":2.81,"akreditasi":{"nilai":"Unggul","no_sk":"0517/SK/LAM Teknik/AS/VIII/2025","tahun":"2025","tgl_expired":"2030-08-20","status":"Masih berlaku","jenjang_akred":"S1","match_method":"exact"}},{"no":"35","kode":"17111035","nama":"TEKNIK INFORMATIKA","jenjang":"Sarjana","tampung":64,"peminat":1961,"peluang":3.26,"akreditasi":{"nilai":"Unggul","no_sk":"001/SK/LAM-INFOKOM/Ak.Int/S/XII/2023","tahun":"2023","tgl_expired":"2027-09-30","status":"Masih berlaku","jenjang_akred":"S1","match_method":"exact"}},{"no":"36","kode":"17111036","nama":"FISOTERAPI","jenjang":"Sarjana","tampung":47,"peminat":606,"peluang":7.76,"akreditasi":null},{"no":"37","kode":"17111037","nama":"TEKNIK LINGKUNGAN","jenjang":"Sarjana","tampung":65,"peminat":621,"peluang":10.47,"akreditasi":{"nilai":"Unggul","no_sk":"0623/SK/LAM Teknik/AS/XII/2024","tahun":"2024","tgl_expired":"2029-12-20","status":"Masih berlaku","jenjang_akred":"S1","match_method":"exact"}},{"no":"38","kode":"17111038","nama":"KEDOKTERAN HEWAN","jenjang":"Sarjana","tampung":65,"peminat":550,"peluang":11.82,"akreditasi":{"nilai":"UNGGUL","no_sk":"0448/LAM-PTKes/Akr/Sar/III/2025","tahun":"2025","tgl_expired":"2030-03-20","status":"Masih berlaku","jenjang_akred":"S1","match_method":"exact"}},{"no":"39","kode":"17111039","nama":"PSIKOLOGI","jenjang":"Sarjana","tampung":53,"peminat":1095,"peluang":4.84,"akreditasi":{"nilai":"B","no_sk":"7907/SK/BAN-PT/PEPA-Ppj/S/X/2025","tahun":"2025","tgl_expired":"2030-10-07","status":"Masih berlaku","jenjang_akred":"S1","match_method":"exact"}},{"no":"40","kode":"17111040","nama":"SISTEM INFORMASI","jenjang":"Sarjana","tampung":58,"peminat":833,"peluang":6.96,"akreditasi":{"nilai":"Baik Sekali","no_sk":"021/SK/LAM-INFOKOM/Ak.B/S/III/2024","tahun":"2024","tgl_expired":"2029-03-26","status":"Masih berlaku","jenjang_akred":"S1","match_method":"exact"}},{"no":"41","kode":"17111041","nama":"ILMU AKTUARIA","jenjang":"Sarjana","tampung":53,"peminat":247,"peluang":21.46,"akreditasi":{"nilai":"Baik","no_sk":"11530/SK/BAN-PT/Akred/S/X/2021","tahun":"2021","tgl_expired":"2026-10-12","status":"Masih berlaku","jenjang_akred":"S1","match_method":"partial"}},{"no":"42","kode":"17111042","nama":"REKAYASA KEHUTANAN","jenjang":"Sarjana","tampung":54,"peminat":113,"peluang":47.79,"akreditasi":{"nilai":"Baik","no_sk":"1530/SK/BAN-PT/Ak/S/IV/2023","tahun":"2023","tgl_expired":"2028-04-26","status":"Masih berlaku","jenjang_akred":"S1","match_method":"exact"}},{"no":"43","kode":"17111045","nama":"ILMU TANAH","jenjang":"Sarjana","tampung":85,"peminat":170,"peluang":50.0,"akreditasi":{"nilai":"Baik","no_sk":"1904/SK/BAN-PT/Ak/S/V/2023","tahun":"2023","tgl_expired":"2028-05-23","status":"Masih berlaku","jenjang_akred":"S1","match_method":"exact"}},{"no":"44","kode":"17111046","nama":"PROTEKSI TANAMAN","jenjang":"Sarjana","tampung":82,"peminat":133,"peluang":61.65,"akreditasi":{"nilai":"Baik","no_sk":"3530/SK/BAN-PT/Ak/S/IX/2023","tahun":"2023","tgl_expired":"2028-09-05","status":"Masih berlaku","jenjang_akred":"S1","match_method":"exact"}},{"no":"45","kode":"17111047","nama":"KONSERVASI HUTAN","jenjang":"Sarjana","tampung":43,"peminat":78,"peluang":55.13,"akreditasi":{"nilai":"Baik","no_sk":"342/SK/BAN-PT/Ak/S/II/2024","tahun":"2024","tgl_expired":"2029-02-06","status":"Masih berlaku","jenjang_akred":"S1","match_method":"exact"}},{"no":"46","kode":"17111048","nama":"TEKNOLOGI HASIL PERIKANAN","jenjang":"Sarjana","tampung":47,"peminat":62,"peluang":75.81,"akreditasi":{"nilai":"Baik","no_sk":"4705/SK/BAN-PT/Ak/S/XI/2023","tahun":"2023","tgl_expired":"2028-11-14","status":"Masih berlaku","jenjang_akred":"S1","match_method":"exact"}},{"no":"47","kode":"17111054","nama":"MANAJEMEN","jenjang":"Sarjana","tampung":154,"peminat":1739,"peluang":8.86,"akreditasi":{"nilai":"Unggul","no_sk":"491/DE/A.5/AR.10/VI/2023","tahun":"2023","tgl_expired":"2028-06-23","status":"Masih berlaku","jenjang_akred":"S1","match_method":"exact"}},{"no":"48","kode":"17111055","nama":"ILMU HUKUM","jenjang":"Sarjana","tampung":178,"peminat":2477,"peluang":7.19,"akreditasi":{"nilai":"Unggul","no_sk":"5243/SK/BAN-PT/Ak-PPJ/S/VIII/2022","tahun":"2022","tgl_expired":"2027-08-16","status":"Masih berlaku","jenjang_akred":"S1","match_method":"exact"}},{"no":"49","kode":"17111056","nama":"ILMU POLITIK","jenjang":"Sarjana","tampung":46,"peminat":306,"peluang":15.03,"akreditasi":{"nilai":"Unggul","no_sk":"2854/SK/BAN-PT/Ak.Ppj/S/VII/2023","tahun":"2023","tgl_expired":"2028-08-02","status":"Masih berlaku","jenjang_akred":"S1","match_method":"exact"}},{"no":"50","kode":"17111057","nama":"ANTROPOLOGI","jenjang":"Sarjana","tampung":62,"peminat":161,"peluang":38.51,"akreditasi":{"nilai":"Unggul","no_sk":"3397/SK/BAN-PT/Ak-PPJ/S/V/2022","tahun":"2022","tgl_expired":"2027-05-19","status":"Masih berlaku","jenjang_akred":"S1","match_method":"exact"}},{"no":"51","kode":"17111058","nama":"ILMU SEJARAH","jenjang":"Sarjana","tampung":46,"peminat":131,"peluang":35.11,"akreditasi":{"nilai":"Unggul","no_sk":"4381/SK/BAN-PT/Ak.Ppj/S/V/2024","tahun":"2024","tgl_expired":"2029-05-30","status":"Masih berlaku","jenjang_akred":"S1","match_method":"exact"}},{"no":"52","kode":"17111059","nama":"ILMU KOMUNIKASI","jenjang":"Sarjana","tampung":71,"peminat":1062,"peluang":6.69,"akreditasi":{"nilai":"Unggul","no_sk":"1369/SK/BAN-PT/Ak.Ppj/S/IV/2023","tahun":"2023","tgl_expired":"2028-04-25","status":"Masih berlaku","jenjang_akred":"S1","match_method":"exact"}},{"no":"53","kode":"17111060","nama":"SOSIOLOGI","jenjang":"Sarjana","tampung":71,"peminat":219,"peluang":32.42,"akreditasi":{"nilai":"A","no_sk":"2513/SK/BAN-PT/Ak-PPJ/S/IV/2022","tahun":"2022","tgl_expired":"2027-04-26","status":"Masih berlaku","jenjang_akred":"S1","match_method":"exact"}},{"no":"54","kode":"17111061","nama":"AKUNTANSI","jenjang":"Sarjana","tampung":130,"peminat":1326,"peluang":9.8,"akreditasi":{"nilai":"Unggul","no_sk":"661/DE/A.5/AR.10/VIII/2023","tahun":"2023","tgl_expired":"2028-08-31","status":"Masih berlaku","jenjang_akred":"Sarjana","match_method":"exact"}},{"no":"55","kode":"17111062","nama":"ILMU PEMERINTAHAN","jenjang":"Sarjana","tampung":65,"peminat":437,"peluang":14.87,"akreditasi":{"nilai":"Unggul","no_sk":"2510/SK/BAN-PT/Ak-PPJ/S/IV/2022","tahun":"2022","tgl_expired":"2027-05-03","status":"Masih berlaku","jenjang_akred":"S1","match_method":"exact"}},{"no":"56","kode":"17111063","nama":"ILMU HUBUNGAN INTERNASIONAL","jenjang":"Sarjana","tampung":70,"peminat":667,"peluang":10.49,"akreditasi":{"nilai":"Unggul","no_sk":"043/AK.03.05/2026","tahun":"2026","tgl_expired":"2030-11-02","status":"Masih berlaku","jenjang_akred":"S1","match_method":"exact"}},{"no":"57","kode":"17111064","nama":"ADMINISTRASI PUBLIK","jenjang":"Sarjana","tampung":60,"peminat":761,"peluang":7.88,"akreditasi":{"nilai":"Unggul","no_sk":"326/AK.03.01/2025","tahun":"2025","tgl_expired":"2026-06-29","status":"85 hari lagi kadaluarsa","jenjang_akred":"S1","match_method":"exact"}},{"no":"58","kode":"17111065","nama":"SASTRA INDONESIA","jenjang":"Sarjana","tampung":75,"peminat":218,"peluang":34.4,"akreditasi":{"nilai":"Unggul","no_sk":"5194/SK/BAN-PT/Ak.Ppj/S/VII/2024","tahun":"2024","tgl_expired":"2029-08-14","status":"Masih berlaku","jenjang_akred":"S1","match_method":"exact"}},{"no":"59","kode":"17111066","nama":"SASTRA DAERAH","jenjang":"Sarjana","tampung":17,"peminat":26,"peluang":65.38,"akreditasi":{"nilai":"Baik Sekali","no_sk":"7532/SK/BAN-PT/Ak.S/S/IX/2025","tahun":"2025","tgl_expired":"-","status":"Masih berlaku","jenjang_akred":"S1","match_method":"exact"}},{"no":"60","kode":"17111067","nama":"SASTRA ARAB","jenjang":"Sarjana","tampung":45,"peminat":183,"peluang":24.59,"akreditasi":{"nilai":"Unggul","no_sk":"1464/SK/BAN-PT/Ak.Ppj/S/IV/2023","tahun":"2023","tgl_expired":"2028-05-03","status":"Masih berlaku","jenjang_akred":"S1","match_method":"exact"}},{"no":"61","kode":"17111068","nama":"SASTRA INGGRIS","jenjang":"Sarjana","tampung":99,"peminat":517,"peluang":19.15,"akreditasi":{"nilai":"Unggul","no_sk":"8535/SK/BAN-PT/Ak.KP/S/XII/2025","tahun":"2025","tgl_expired":"2029-07-24","status":"Masih berlaku","jenjang_akred":"S1","match_method":"exact"}},{"no":"62","kode":"17111069","nama":"SASTRA PERANCIS","jenjang":"Sarjana","tampung":17,"peminat":39,"peluang":43.59,"akreditasi":{"nilai":"B","no_sk":"10521/SK/BAN-PT/Ak-PPJ/S/VIII/2021","tahun":"2021","tgl_expired":"2026-08-27","status":"144 hari lagi kadaluarsa","jenjang_akred":"S1","match_method":"exact"}},{"no":"63","kode":"17111070","nama":"ARKEOLOGI","jenjang":"Sarjana","tampung":60,"peminat":144,"peluang":41.67,"akreditasi":{"nilai":"Unggul","no_sk":"6546/SK/BAN-PT/Ak.KP/S/XI/2024","tahun":"2024","tgl_expired":"2026-09-30","status":"178 hari lagi kadaluarsa","jenjang_akred":"S1","match_method":"exact"}},{"no":"64","kode":"17111071","nama":"SASTRA JEPANG","jenjang":"Sarjana","tampung":84,"peminat":267,"peluang":31.46,"akreditasi":{"nilai":"Unggul","no_sk":"560/SK/BAN-PT/Ak.KP/S/II/2024","tahun":"2024","tgl_expired":"2028-08-08","status":"Masih berlaku","jenjang_akred":"S1","match_method":"exact"}},{"no":"65","kode":"17111072","nama":"EKONOMI PEMBANGUNAN","jenjang":"Sarjana","tampung":135,"peminat":553,"peluang":24.41,"akreditasi":{"nilai":"Unggul","no_sk":"2654/DE/A.5/AR.10/VIII/2025","tahun":"2025","tgl_expired":"2030-08-25","status":"Masih berlaku","jenjang_akred":"S1","match_method":"exact"}},{"no":"66","kode":"17111073","nama":"HUKUM ADMINISTRASI NEGARA","jenjang":"Sarjana","tampung":36,"peminat":613,"peluang":5.87,"akreditasi":{"nilai":"B","no_sk":"353/SK/BAN-PT/Ak.Ppj/S/III/2025","tahun":"2025","tgl_expired":"2030-03-16","status":"Masih berlaku","jenjang_akred":"S1","match_method":"exact"}},{"no":"67","kode":"17111074","nama":"BAHASA MANDARIN DAN KEBUDAYAAN TIONGKOK","jenjang":"Sarjana","tampung":68,"peminat":313,"peluang":21.73,"akreditasi":{"nilai":"Baik","no_sk":"232/SK/BAN-PT/Ak.Ppj/S/II/2026","tahun":"2026","tgl_expired":"2031-02-18","status":"Masih berlaku","jenjang_akred":"S1","match_method":"exact"}},{"no":"68","kode":"17111077","nama":"PARIWISATA","jenjang":"Sarjana","tampung":54,"peminat":360,"peluang":15.0,"akreditasi":{"nilai":"Baik","no_sk":"6502/SK/BAN-PT/Ak/S/X/2024","tahun":"2024","tgl_expired":"2029-10-29","status":"Masih berlaku","jenjang_akred":"S1","match_method":"exact"}},{"no":"69","kode":"17111080","nama":"EKONOMI DAN BISNIS ISLAM","jenjang":"Sarjana","tampung":38,"peminat":340,"peluang":11.18,"akreditasi":{"nilai":"Baik","no_sk":"117/DE/A.5/AR.11/I/2024","tahun":"2024","tgl_expired":"2029-01-16","status":"Masih berlaku","jenjang_akred":"S1","match_method":"exact"}},{"no":"70","kode":"17111081","nama":"TEKNOLOGI INDUSTRI PERTANIAN","jenjang":"Sarjana","tampung":45,"peminat":159,"peluang":28.3,"akreditasi":{"nilai":"Terakreditasi Sementara","no_sk":"7178/SK/BAN-PT/Ak.P/2.0/S1/IX/2025","tahun":"2025","tgl_expired":"2030-09-09","status":"Masih berlaku","jenjang_akred":"S1","match_method":"exact"}},{"no":"71","kode":"17111084","nama":"TEKNIK GEODESI","jenjang":"Sarjana","tampung":36,"peminat":121,"peluang":29.75,"akreditasi":{"nilai":"Baik","no_sk":"0543/SK/LAM Teknik/AS/IX/2024","tahun":"2024","tgl_expired":"2026-09-12","status":"160 hari lagi kadaluarsa","jenjang_akred":"S1","match_method":"exact"}},{"no":"72","kode":"17111085","nama":"TEKNIK METALURGI DAN MATERIAL","jenjang":"Sarjana","tampung":40,"peminat":508,"peluang":7.87,"akreditasi":{"nilai":"Baik","no_sk":"0246/SK/LAM Teknik/AS/V/2024","tahun":"2024","tgl_expired":"2026-05-15","status":"40 hari lagi kadaluarsa","jenjang_akred":"S1","match_method":"exact"}},{"no":"73","kode":"17111087","nama":"PEMULIAAN DAN BIOTEKNOLOGI TANAMAN","jenjang":"Sarjana","tampung":17,"peminat":null,"peluang":null,"akreditasi":{"nilai":"Terakreditasi Pertama","no_sk":"079/SK/BAN-PT/Ak.P/2.0/S1/XII/2025","tahun":"2025","tgl_expired":"2027-12-02","status":"Masih berlaku","jenjang_akred":"S1","match_method":"exact"}},{"no":"74","kode":"17111088","nama":"PEMBANGUNAN PERTANIAN","jenjang":"Sarjana","tampung":17,"peminat":null,"peluang":null,"akreditasi":{"nilai":"Terakreditasi Sementara","no_sk":"008/SK/BAN-PT/Ak.P/2.0/S1/X/2025","tahun":"2025","tgl_expired":"2030-10-06","status":"Masih berlaku","jenjang_akred":"S1","match_method":"exact"}},{"no":"75","kode":"17111089","nama":"ILMU PERPUSTAKAAN DAN SAINS INFORMASI","jenjang":"Sarjana","tampung":26,"peminat":null,"peluang":null,"akreditasi":{"nilai":"Terakreditasi Sementara","no_sk":"007/AK.03.02/2026","tahun":"2026","tgl_expired":"2029-10-17","status":"Masih berlaku","jenjang_akred":"S1","match_method":"exact"}},{"no":"76","kode":"17112043","nama":"TEKNOLOGI PRODUKSI TERNAK","jenjang":"Sarjana Terapan","tampung":24,"peminat":70,"peluang":34.29,"akreditasi":null},{"no":"77","kode":"17112044","nama":"TEKNOLOGI PRODUKSI TANAMAN PANGAN","jenjang":"Sarjana Terapan","tampung":26,"peminat":232,"peluang":11.21,"akreditasi":null},{"no":"78","kode":"17112049","nama":"AGRIBISNIS PANGAN","jenjang":"Sarjana Terapan","tampung":39,"peminat":631,"peluang":6.18,"akreditasi":null},{"no":"79","kode":"17112050","nama":"TEKNOLOGI PAKAN TERNAK","jenjang":"Sarjana Terapan","tampung":24,"peminat":93,"peluang":25.81,"akreditasi":null},{"no":"80","kode":"17112051","nama":"AGRIBISNIS PETERNAKAN","jenjang":"Sarjana Terapan","tampung":34,"peminat":306,"peluang":11.11,"akreditasi":null},{"no":"81","kode":"17112052","nama":"TERAPI GIGI","jenjang":"Sarjana Terapan","tampung":32,"peminat":1132,"peluang":2.83,"akreditasi":null},{"no":"82","kode":"17112053","nama":"BUDI DAYA LAUT DAN PANTAI","jenjang":"Sarjana Terapan","tampung":20,"peminat":175,"peluang":11.43,"akreditasi":null},{"no":"83","kode":"17112075","nama":"DESTINASI PARIWISATA","jenjang":"Sarjana Terapan","tampung":27,"peminat":739,"peluang":3.65,"akreditasi":null},{"no":"84","kode":"17112078","nama":"TEKNOLOGI AKUAKULTUR DAN PASCA PANEN PERIKANAN","jenjang":"Sarjana Terapan","tampung":31,"peminat":80,"peluang":38.75,"akreditasi":null},{"no":"85","kode":"17112079","nama":"PARAMEDIK VETERINER","jenjang":"Sarjana Terapan","tampung":33,"peminat":178,"peluang":18.54,"akreditasi":null},{"no":"86","kode":"17112082","nama":"TEKNOLOGI METALURGI EKSTRAKSI","jenjang":"Sarjana Terapan","tampung":21,"peminat":626,"peluang":3.35,"akreditasi":null},{"no":"87","kode":"17112083","nama":"PENGINDERAAN JAUH DAN SISTEM INFORMASI GEOGRAFIS","jenjang":"Sarjana Terapan","tampung":43,"peminat":300,"peluang":14.33,"akreditasi":null},{"no":"88","kode":"17112086","nama":"KOMUNIKASI DIGITAL","jenjang":"Sarjana Terapan","tampung":15,"peminat":null,"peluang":null,"akreditasi":null}]}